snakemake_storage_plugin_http/__init__.py
snakemake_storage_plugin_http-0.3.0.dist-info/LICENSE
snakemake_storage_plugin_http-0.3.0.dist-info/METADATA
snakemake_storage_plugin_http-0.3.0.dist-info/WHEEL
snakemake_storage_plugin_http-0.3.0.dist-info/RECORD
